dht_node/__init__.py
dht_node/data_structures.py
dht_node/dht_node.py
dht_node/py.typed
dht_node/routing_table.py
dht_node/utils.py
simple_dht_node-1.2.2.dist-info/LICENSE
simple_dht_node-1.2.2.dist-info/METADATA
simple_dht_node-1.2.2.dist-info/WHEEL
simple_dht_node-1.2.2.dist-info/top_level.txt
simple_dht_node-1.2.2.dist-info/RECORD
