Metadata-Version: 2.1
Name: simple-dht-node
Version: 1.2.2
Summary: A simple Bittorrent DHT node
Home-page: https://github.com/retonato/simple-dht-node
License: UNKNOWN
Platform: UNKNOWN
Requires-Python: >=3.7
Requires-Dist: cachetools
Requires-Dist: modern-bencode
